{
    "AX": {
        "error": 0.05201443258833445, 
        "filter_outliers_dict": {
            "filter_outliers": true, 
            "iterations": 1, 
            "std_devs": 2
        }, 
        "fit": "average", 
        "value": -0.20749252203818971
    }, 
    "CDD": {
        "error": 2.7061047566066653e-05, 
        "filter_outliers_dict": {
            "filter_outliers": true, 
            "iterations": 1, 
            "std_devs": 10
        }, 
        "fit": "average", 
        "value": 5.004128615837544e-06
    }, 
    "H1": {
        "error": 0.04042604964846824, 
        "filter_outliers_dict": {
            "filter_outliers": true, 
            "iterations": 1, 
            "std_devs": 2
        }, 
        "fit": "average", 
        "value": -0.05034528836531855
    }, 
    "H2": {
        "error": 0.09992839356934793, 
        "filter_outliers_dict": {
            "filter_outliers": true, 
            "iterations": 1, 
            "std_devs": 2
        }, 
        "fit": "average", 
        "value": -0.19477944880960868
    }, 
    "L1": {
        "error": 0.023388441771468475, 
        "filter_outliers_dict": {
            "filter_outliers": true, 
            "iterations": 1, 
            "std_devs": 2
        }, 
        "fit": "average", 
        "value": -0.04084574958768725
    }, 
    "L2": {
        "error": 0.04028291953706317, 
        "filter_outliers_dict": {
            "filter_outliers": true, 
            "iterations": 1, 
            "std_devs": 2
        }, 
        "fit": "average", 
        "value": -0.026571121188551063
    }
}